botaclan/__init__.py
botaclan/__main__.py
botaclan/cogs/__init__.py
botaclan/cogs/calendar.py
botaclan/cogs/roulette.py
botaclan/constants.py
botaclan/google/__init__.py
botaclan/google/auth.py
botaclan/google/google_calendar.py
botaclan/helpers/__init__.py
botaclan/helpers/date.py
botaclan/helpers/lists.py
botaclan/helpers/text.py
botaclan-0.1.0.dist-info/entry_points.txt
botaclan-0.1.0.dist-info/LICENSE
botaclan-0.1.0.dist-info/WHEEL
botaclan-0.1.0.dist-info/METADATA
botaclan-0.1.0.dist-info/RECORD
