Metadata-Version: 2.1
Name: botaclan
Version: 0.1.0
Summary: Bataclan's official bot
Home-page: https://github.com/bataclanofficial/botaclan
License: Apache-2.0
Keywords: discord,bataclan,python,bot
Author: Gabriel Tiossi
Author-email: gabrieltiossi@gmail.com
Requires-Python: >=3.8,<4.0
Classifier: Development Status :: 1 - Planning
Classifier: License :: OSI Approved :: Apache Software License
Classifier: Programming Language :: Python :: 3
Classifier: Programming Language :: Python :: 3.8
Classifier: Topic :: Communications :: Chat
Requires-Dist: coloredlogs (>=14.0,<15.0)
Requires-Dist: dateparser (>=0.7.4,<0.8.0)
Requires-Dist: discord.py (>=1.3.3,<2.0.0)
Requires-Dist: google-api-python-client (>=1.8.3,<2.0.0)
Requires-Dist: google-auth-httplib2 (>=0.0.3,<0.0.4)
Requires-Dist: google-auth-oauthlib (>=0.4.1,<0.5.0)
Requires-Dist: importlib-metadata (>=1.6.0,<2.0.0)
Requires-Dist: sentry-sdk (>=0.14.4,<0.15.0)
Requires-Dist: vyper-config (>=0.6.2,<0.7.0)
Project-URL: Repository, https://github.com/bataclanofficial/botaclan
